aiolyric/__init__.py
aiolyric/const.py
aiolyric/exceptions.py
aiolyric/client/__init__.py
aiolyric/objects/__init__.py
aiolyric/objects/base.py
aiolyric/objects/device.py
aiolyric/objects/location.py
aiolyric/objects/priority.py
dalinicus.aiolyric-1.1.6.dist-info/LICENSE
dalinicus.aiolyric-1.1.6.dist-info/METADATA
dalinicus.aiolyric-1.1.6.dist-info/WHEEL
dalinicus.aiolyric-1.1.6.dist-info/top_level.txt
dalinicus.aiolyric-1.1.6.dist-info/RECORD
