Metadata-Version: 2.1
Name: dalinicus.aiolyric
Version: 1.1.6
Summary: AIO package for the Honeywell Lyric Platform.
Home-page: https://github.com/timmo001/aiolyric
Author: Aidan Timson (Timmo)
Author-email: contact@timmo.xyz
License: MIT
Keywords: honeywell lyric thermostat
License-File: LICENSE
Requires-Dist: aiohttp (>=3.7.3)
